dypendence/__init__.py
dypendence/dypendence.py
dypendence-0.1.6.dist-info/LICENSE
dypendence-0.1.6.dist-info/WHEEL
dypendence-0.1.6.dist-info/METADATA
dypendence-0.1.6.dist-info/RECORD
