Metadata-Version: 2.1
Name: dypendence
Version: 0.1.6
Summary: Dependency Injection over Dynaconf
Home-page: https://github.com/VaultVulp/dypendence
License: MIT
Author: VaultVulp
Author-email: me@vaultvulp.dev
Requires-Python: >=3.8,<4.0
Classifier: License :: OSI Approved :: MIT License
Classifier: Programming Language :: Python :: 3
Classifier: Programming Language :: Python :: 3.8
Classifier: Programming Language :: Python :: 3.9
Requires-Dist: dynaconf (>=3.1.2,<4.0.0)
Project-URL: Repository, https://github.com/VaultVulp/dypendence
